dicomexporter/__init__.py
dicomexporter/cli.py
dicomexporter/dicom.py
dicomexporter/exporter.py
dicomexporter/itk_utils.py
dicom_exporter-1.0.0.dist-info/LICENSE
dicom_exporter-1.0.0.dist-info/METADATA
dicom_exporter-1.0.0.dist-info/WHEEL
dicom_exporter-1.0.0.dist-info/entry_points.txt
dicom_exporter-1.0.0.dist-info/top_level.txt
dicom_exporter-1.0.0.dist-info/RECORD
