Metadata-Version: 2.1
Name: dicom_exporter
Version: 1.0.0
Summary: Program to export dicom files to .vti or .vtkjs
Home-page: https://github.com/KitwareMedical/dicom-exporter
Author: Julien Finet
Author-email: julien.finet@kitware.com
Keywords: dicom exporter medical
Classifier: Development Status :: 3 - Alpha
Classifier: Intended Audience :: Science/Research
Classifier: Topic :: Software Development :: Build Tools
Classifier: License :: OSI Approved :: BSD License
Classifier: Natural Language :: English
Classifier: Programming Language :: Python
License-File: LICENSE
Requires-Dist: itk
Requires-Dist: vtk
Requires-Dist: numpy
